{
  "id": "44b64fd9-7634-47de-bcfe-0c6b7a70a05a",
  "prevId": "628d39f2-06d7-4189-80cc-c5395904da80",
  "version": "7",
  "dialect": "postgresql",
  "tables": {
    "public.songs": {
      "name": "songs",
      "schema": "",
      "columns": {
        "id": {
          "name": "id",
          "type": "serial",
          "primaryKey": true,
          "notNull": true
        },
        "title": {
          "name": "title",
          "type": "varchar(255)",
          "primaryKey": false,
          "notNull": true
        },
        "artist": {
          "name": "artist",
          "type": "varchar(255)",
          "primaryKey": false,
          "notNull": true
        },
        "notes": {
          "name": "notes",
          "type": "text",
          "primaryKey": false,
          "notNull": false
        },
        "genres": {
          "name": "genres",
          "type": "varchar(500)",
          "primaryKey": false,
          "notNull": false
        },
        "link": {
          "name": "link",
          "type": "varchar(500)",
          "primaryKey": false,
          "notNull": false
        },
        "link_type": {
          "name": "link_type",
          "type": "varchar(20)",
          "primaryKey": false,
          "notNull": false
        },
        "submitted_at": {
          "name": "submitted_at",
          "type": "timestamp",
          "primaryKey": false,
          "notNull": true,
          "default": "now()"
        },
        "status": {
          "name": "status",
          "type": "varchar(50)",
          "primaryKey": false,
          "notNull": true,
          "default": "'pending'"
        },
        "points": {
          "name": "points",
          "type": "integer",
          "primaryKey": false,
          "notNull": true,
          "default": 1
        },
        "banana_sticker": {
          "name": "banana_sticker",
          "type": "boolean",
          "primaryKey": false,
          "notNull": true,
          "default": false
        },
        "submitter_id": {
          "name": "submitter_id",
          "type": "varchar(255)",
          "primaryKey": false,
          "notNull": false
        },
        "archived_at": {
          "name": "archived_at",
          "type": "timestamp",
          "primaryKey": false,
          "notNull": false
        }
      },
      "indexes": {},
      "foreignKeys": {},
      "compositePrimaryKeys": {},
      "uniqueConstraints": {},
      "policies": {},
      "checkConstraints": {},
      "isRLSEnabled": false
    }
  },
  "enums": {},
  "schemas": {},
  "sequences": {},
  "roles": {},
  "policies": {},
  "views": {},
  "_meta": {
    "columns": {},
    "schemas": {},
    "tables": {}
  }
}